{
  "vRule": "r00.00.001",
  "vSchemaN": "s00.00.001",
  "board": {
    "specialPits": "[]",
    "pitsPerSide": {
      "Type": "integer",
      "Param": {
        "Default": "7",
        "Value": "7",
        "Enabled": true,
        "Config": "fixed",
        "Min": "7",
        "Max": "7"
      }
    },
    "nSide": {
      "Type": "integer",
      "Param": {
        "Default": "2",
        "Value": "2",
        "Enabled": true,
        "Config": "fixed",
        "Min": "2",
        "Max": "2"
      }
    },
    "nSeeds": {
      "Type": "integer",
      "Param": {
        "Default": "6",
        "Value": "6",
        "Enabled": true,
        "Config": "fixed",
        "Min": "6",
        "Max": "6"
      }
    }
  },
  "algorithm": {
    "Type": "enum",
    "SubType": "classic",
    "Param": {
      "Default": "classic",
      "Value": "classic",
      "Enabled": true,
      "Config": "",
      "Min": "classic",
      "Max": "classic"
    }
  },
  "capture": {
    "Type": "enum",
    "SubType": "beyond",
    "Param": {
      "Default": "beyond",
      "Value": "beyond",
      "Enabled": true,
      "Config": "fixed",
      "Min": "beyond",
      "Max": "beyond"
    }
  },
  "timelimit": {
    "Type": "integer",
    "Param": {
      "Default": "100",
      "Value": "01000",
      "Enabled": false,
      "Config": "",
      "Min": "1000",
      "Max": "10000"
    }
  },
  "nPlayers": {
    "Type": "integer",
    "Param": {
      "Default": "2",
      "Value": "2",
      "Enabled": true,
      "Config": "fixed",
      "Min": "2",
      "Max": "2"
    }
  },
  "direction": {
    "Param": {
      "Default": "1",
      "Value": "1",
      "Enabled": true,
      "Config": "fixed",
      "Min": "1",
      "Max": "1"
    }
  },
  "mod": {
    "Type": "integer",
    "Param": {
      "Default": "5",
      "Value": "5",
      "Enabled": true,
      "Config": "fixed",
      "Min": "5",
      "Max": "5"
    }
  }
}